embryo/__init__.py
embryo/constants.py
embryo/dot.py
embryo/embryo.py
embryo/environment.py
embryo/exceptions.py
embryo/filesystem.py
embryo/history.py
embryo/incubator.py
embryo/logging.py
embryo/relationship.py
embryo/renderer.py
embryo/utils.py
embryo/cli/__init__.py
embryo/cli/app.py
embryo/cli/command.py
embryo/cli/util.py
embryo-3.0.1.data/scripts/embryo
embryo-3.0.1.data/scripts/hatch
embryo-3.0.1.dist-info/LICENSE
embryo-3.0.1.dist-info/METADATA
embryo-3.0.1.dist-info/WHEEL
embryo-3.0.1.dist-info/top_level.txt
embryo-3.0.1.dist-info/RECORD
