Metadata-Version: 2.1
Name: embryo
Version: 3.0.1
Summary: Embryo renderer scaffold engine
Home-page: https://github.com/gigaquads/embryo.git
Author: Gigaquads
Author-email: what@gigaquads.com
License: UNKNOWN
Platform: UNKNOWN
Classifier: Programming Language :: Python :: 3.9
Classifier: License :: OSI Approved :: MIT License
Requires-Dist: ravel
Requires-Dist: appyratus
Requires-Dist: tabulate
Requires-Dist: pytest
Requires-Dist: ipdb
